sopel_modules.quiz-0.1.0-py3.7-nspkg.pth
sopel_modules/quiz/__init__.py
sopel_modules/quiz/quiz.py
tests/__init__.py
tests/test_quiz.py
sopel_modules.quiz-0.1.0.dist-info/COPYING
sopel_modules.quiz-0.1.0.dist-info/METADATA
sopel_modules.quiz-0.1.0.dist-info/WHEEL
sopel_modules.quiz-0.1.0.dist-info/namespace_packages.txt
sopel_modules.quiz-0.1.0.dist-info/top_level.txt
sopel_modules.quiz-0.1.0.dist-info/RECORD
