Metadata-Version: 2.1
Name: sopel-modules.quiz
Version: 0.1.0
Summary: A quiz using questions from jservice.io
Home-page: https://github.com/shanedabes/sopel-quiz
Author: Shane Donohoe
Author-email: shane@donohoe.cc
License: Eiffel Forum License, version 2
Platform: UNKNOWN
Requires-Dist: sopel (<7,>=6.0)
